yowsup/__init__.py
yowsup/axolotl/__init__.py
yowsup/axolotl/exceptions.py
yowsup/axolotl/factory.py
yowsup/axolotl/manager.py
yowsup/axolotl/store/__init__.py
yowsup/axolotl/store/sqlite/__init__.py
yowsup/axolotl/store/sqlite/liteaxolotlstore.py
yowsup/axolotl/store/sqlite/liteidentitykeystore.py
yowsup/axolotl/store/sqlite/liteprekeystore.py
yowsup/axolotl/store/sqlite/litesenderkeystore.py
yowsup/axolotl/store/sqlite/litesessionstore.py
yowsup/axolotl/store/sqlite/litesignedprekeystore.py
yowsup/common/__init__.py
yowsup/common/constants.py
yowsup/common/mime.types
yowsup/common/optionalmodules.py
yowsup/common/tools.py
yowsup/common/http/__init__.py
yowsup/common/http/httpproxy.py
yowsup/common/http/test_warequest.py
yowsup/common/http/warequest.py
yowsup/common/http/waresponseparser.py
yowsup/config/__init__.py
yowsup/config/manager.py
yowsup/config/base/__init__.py
yowsup/config/base/config.py
yowsup/config/base/serialize.py
yowsup/config/base/transform.py
yowsup/config/transforms/__init__.py
yowsup/config/transforms/config_dict.py
yowsup/config/transforms/dict_json.py
yowsup/config/transforms/dict_keyval.py
yowsup/config/transforms/filter.py
yowsup/config/transforms/map.py
yowsup/config/transforms/meta.py
yowsup/config/transforms/props.py
yowsup/config/transforms/serialize.py
yowsup/config/v1/__init__.py
yowsup/config/v1/config.py
yowsup/config/v1/serialize.py
yowsup/demos/__init__.py
yowsup/demos/cli/__init__.py
yowsup/demos/cli/cli.py
yowsup/demos/cli/layer.py
yowsup/demos/cli/stack.py
yowsup/demos/common/__init__.py
yowsup/demos/common/sink_worker.py
yowsup/demos/contacts/__init__.py
yowsup/demos/contacts/layer.py
yowsup/demos/contacts/stack.py
yowsup/demos/echoclient/__init__.py
yowsup/demos/echoclient/layer.py
yowsup/demos/echoclient/stack.py
yowsup/demos/mediasink/__init__.py
yowsup/demos/mediasink/layer.py
yowsup/demos/mediasink/stack.py
yowsup/demos/sendclient/__init__.py
yowsup/demos/sendclient/layer.py
yowsup/demos/sendclient/stack.py
yowsup2-3.2.2.dist-info/LICENSE
yowsup2-3.2.2.dist-info/METADATA
yowsup2-3.2.2.dist-info/WHEEL
yowsup2-3.2.2.dist-info/top_level.txt
yowsup2-3.2.2.dist-info/RECORD
